LICENSE
MANIFEST.in
README.md
package.json
setup.py
dash_react_editable_json_tree/DashReactEditableJsonTree.py
dash_react_editable_json_tree/__init__.py
dash_react_editable_json_tree/_imports_.py
dash_react_editable_json_tree/dash_react_editable_json_tree.min.js
dash_react_editable_json_tree/dash_react_editable_json_tree.min.js.map
dash_react_editable_json_tree/metadata.json
dash_react_editable_json_tree/package-info.json
dash_react_editable_json_tree.egg-info/PKG-INFO
dash_react_editable_json_tree.egg-info/SOURCES.txt
dash_react_editable_json_tree.egg-info/dependency_links.txt
dash_react_editable_json_tree.egg-info/top_level.txt