Metadata-Version: 2.1
Name: dash-react-editable-json-tree
Version: 0.0.1
Summary: Project Description
Author: Siddhartha Chakraborty <techiesid1985@gmail.com>
License: MIT
Classifier: Framework :: Dash
License-File: LICENSE
